.hgignore
.installed.cfg
.project
.pydevproject
LICENSE
README.txt
bootstrap.py
buildout.cfg
setup.cfg
setup.py
bin/buildout
bin/test
ztfy/__init__.py
ztfy.monitor.egg-info/PKG-INFO
ztfy.monitor.egg-info/SOURCES.txt
ztfy.monitor.egg-info/dependency_links.txt
ztfy.monitor.egg-info/entry_points.txt
ztfy.monitor.egg-info/namespace_packages.txt
ztfy.monitor.egg-info/not-zip-safe
ztfy.monitor.egg-info/requires.txt
ztfy.monitor.egg-info/top_level.txt
ztfy/monitor/README.txt
ztfy/monitor/__init__.py
ztfy/monitor/configure.zcml
ztfy/monitor/docs/HISTORY.txt
ztfy/monitor/docs/README.txt
ztfy/monitor/doctests/README.txt
ztfy/monitor/tests/__init__.py
ztfy/monitor/tests/test_monitordocs.py
ztfy/monitor/tests/test_monitordocstrings.py