Metadata-Version: 1.0
Name: ztfy.monitor
Version: 0.1
Summary: A zc.z3monitor extension to follow Zope3 server threads activity
Home-page: http://trac.ztfy.org/ztfy.monitor
Author: Thierry Florac
Author-email: tflorac@ulthar.net
License: ZPL
Keywords: ZTFY Zope3 threads monitor
Platform: UNKNOWN
Classifier: License :: OSI Approved :: Zope Public License
Classifier: Development Status :: 4 - Beta
Classifier: Programming Language :: Python
Classifier: Framework :: Zope3
Classifier: Topic :: Software Development :: Libraries :: Python Modules
